adbx/__init__.py
adbx/__main__.py
adbx/bin/platform-tools/NOTICE.txt
adbx/bin/platform-tools/adb
adbx/bin/platform-tools/dmtracedump
adbx/bin/platform-tools/etc1tool
adbx/bin/platform-tools/fastboot
adbx/bin/platform-tools/hprof-conv
adbx/bin/platform-tools/make_f2fs
adbx/bin/platform-tools/make_f2fs_casefold
adbx/bin/platform-tools/mke2fs
adbx/bin/platform-tools/mke2fs.conf
adbx/bin/platform-tools/source.properties
adbx/bin/platform-tools/sqlite3
adbx/bin/platform-tools/lib64/libc++.so
adbx-34.0.1.dist-info/LICENSE
adbx-34.0.1.dist-info/METADATA
adbx-34.0.1.dist-info/WHEEL
adbx-34.0.1.dist-info/entry_points.txt
adbx-34.0.1.dist-info/top_level.txt
adbx-34.0.1.dist-info/RECORD
