Metadata-Version: 2.1
Name: adbx
Version: 34.0.1
Summary: ADB binaries served as Python package.
Author: ysfchn
License: Creative Commons Legal Code
Project-URL: Source Code, https://github.com/ysfchn/adbx
Platform: posix
Platform: windows
Classifier: Programming Language :: Python :: 3.7
Classifier: License :: CC0 1.0 Universal (CC0 1.0) Public Domain Dedication
Classifier: Operating System :: POSIX :: Linux
Classifier: Operating System :: Microsoft :: Windows
Requires-Python: >=3.7
License-File: LICENSE
